homeotopy/__init__.py
homeotopy/_ball.py
homeotopy/_cube.py
homeotopy/_homeomorphism.py
homeotopy/_plane.py
homeotopy/_simplex.py
homeotopy/_sphere.py
homeotopy/py.typed
homeotopy-0.5.0.dist-info/METADATA
homeotopy-0.5.0.dist-info/WHEEL
homeotopy-0.5.0.dist-info/licenses/LICENSE
homeotopy-0.5.0.dist-info/RECORD
