Metadata-Version: 2.4
Name: homeotopy
Version: 0.5.0
Summary: A library for computing homeomorphisms between some common standard topologies
License-File: LICENSE
Keywords: cube,homeomorphism,hypercube,hypersphere,simplex,sphere
Requires-Python: >=3.12
Requires-Dist: numba>=0.61.0
